llmreflect/Agents/BasicAgent.py
llmreflect/Agents/DatabaseAgent.py
llmreflect/Agents/EvaluationAgent.py
llmreflect/Agents/ModerateAgent.py
llmreflect/Agents/QuestionAgent.py
llmreflect/Agents/__init__.py
llmreflect/Chains/BasicChain.py
llmreflect/Chains/DatabaseChain.py
llmreflect/Chains/ModerateChain.py
llmreflect/Chains/__init__.py
llmreflect/LLMCore/LLMCore.py
llmreflect/LLMCore/__init__.py
llmreflect/Prompt/BasicPrompt.py
llmreflect/Prompt/__init__.py
llmreflect/Prompt/promptbase/answer_database copy.json
llmreflect/Prompt/promptbase/answer_database.json
llmreflect/Prompt/promptbase/fix_database.json
llmreflect/Prompt/promptbase/grading_database.json
llmreflect/Prompt/promptbase/moderate_database.json
llmreflect/Prompt/promptbase/question_database.json
llmreflect/Retriever/BasicRetriever.py
llmreflect/Retriever/DatabaseRetriever.py
llmreflect/Retriever/VectorDatabaseRetriever.py
llmreflect/Retriever/__init__.py
llmreflect/Tests/__init__.py
llmreflect/Tests/test_basic_chains.py
llmreflect/Tests/test_combined_chains.py
llmreflect/Tests/test_prompt.py
llmreflect/Tests/test_vb.py
llmreflect/Utils/__init__.py
llmreflect/Utils/database.py
llmreflect/Utils/log.py
llmreflect/__init__.py
llmreflect-0.1.14.dist-info/METADATA
llmreflect-0.1.14.dist-info/WHEEL
llmreflect-0.1.14.dist-info/RECORD
