Metadata-Version: 2.1
Name: llmreflect
Version: 0.1.14
Summary: a package for llm self-reflection
Author: alchemistwu
Author-email: alchemistwu0521@gmail.com
Requires-Python: >=3.10,<4.0
Classifier: Programming Language :: Python :: 3
Classifier: Programming Language :: Python :: 3.10
Classifier: Programming Language :: Python :: 3.11
Classifier: Programming Language :: Python :: 3.12
Requires-Dist: asyncpg
Requires-Dist: boto3
Requires-Dist: botocore
Requires-Dist: chromadb
Requires-Dist: docx2txt
Requires-Dist: flake8 (>=6.1.0,<7.0.0)
Requires-Dist: langchain
Requires-Dist: langchain-community
Requires-Dist: llama-index
Requires-Dist: markdown
Requires-Dist: matplotlib
Requires-Dist: numpy (>=1.25.2,<2.0.0)
Requires-Dist: openai
Requires-Dist: pandas (>=2.1.2,<3.0.0)
Requires-Dist: pdf2image (>=1.16.3,<2.0.0)
Requires-Dist: pgeocode
Requires-Dist: pgvector
Requires-Dist: pillow
Requires-Dist: psycopg2-binary (>=2.9.6,<3.0.0)
Requires-Dist: pydantic
Requires-Dist: pynvml
Requires-Dist: pypdf
Requires-Dist: pypdf2 (>=3.0.1,<4.0.0)
Requires-Dist: pytest (>=7.4.0,<8.0.0)
Requires-Dist: python-decouple
Requires-Dist: python-environ
Requires-Dist: python-pptx
Requires-Dist: s3fs
Requires-Dist: seaborn
Requires-Dist: sqlalchemy
Requires-Dist: tiktoken
Requires-Dist: torch
Requires-Dist: transformers
